gpim/__init__.py
gpim/gprutils.py
gpim/gpbayes/__init__.py
gpim/gpbayes/acqfunc.py
gpim/gpbayes/boptim.py
gpim/gpreg/__init__.py
gpim/gpreg/gpr.py
gpim/gpreg/skgpr.py
gpim/gpreg/vgpr.py
gpim/kernels/__init__.py
gpim/kernels/gpytorch_kernels.py
gpim/kernels/pyro_kernels.py
gpim-0.3.9.dist-info/LICENSE
gpim-0.3.9.dist-info/METADATA
gpim-0.3.9.dist-info/WHEEL
gpim-0.3.9.dist-info/top_level.txt
gpim-0.3.9.dist-info/RECORD
