Metadata-Version: 2.1
Name: gpim
Version: 0.3.9
Summary: Gaussian processes for image analysis
Home-page: https://github.com/ziatdinovmax/GPim
Author: Maxim Ziatdinov
Author-email: maxim.ziatdinov@ai4microcopy.com
License: MIT license
Platform: UNKNOWN
Classifier: Programming Language :: Python
Classifier: Development Status :: 3 - Alpha
Classifier: Intended Audience :: Science/Research
Classifier: Operating System :: OS Independent
Classifier: Topic :: Scientific/Engineering
Requires-Dist: numpy (>=1.16.5)
Requires-Dist: matplotlib (>=3.1.1)
Requires-Dist: torch (>=1.3.1)
Requires-Dist: pyro-ppl (>=0.4.1)
Requires-Dist: gpytorch (>=0.3.6)
Requires-Dist: scikit-image (==0.16.2)
